{
  "title": "RepSpheres Launches Revolutionary AI-Powered Sales Intelligence Platform with 95% Confidence Scoring",
  "content": "FOR IMMEDIATE RELEASE\n\nRepSpheres Launches Revolutionary AI-Powered Sales Intelligence Platform with 95% Confidence Scoring\n\nCanvas Module Transforms Medical Device Sales with Real-Time Doctor Research and Competitive Analysis\n\nSAN FRANCISCO, CA - January 7, 2025 - RepSpheres, an innovative sales intelligence company, today announced the launch of its comprehensive AI-powered platform that revolutionizes how sales teams research prospects and close deals. The platform's flagship Canvas module achieves 95% confidence scoring in doctor research, providing medical device sales teams with unprecedented insights into buying signals, pain points, and competitive landscapes.\n\nThe $50 billion medical device industry has long struggled with inefficient prospect research, with sales reps spending up to 40% of their time gathering basic information about potential clients. RepSpheres changes this paradigm by automating the entire research process, delivering actionable intelligence in under 60 seconds per prospect.\n\n\"Sales teams shouldn't waste hours on Google trying to piece together prospect information,\" said the founder of RepSpheres. \"Our platform uses advanced AI to analyze websites, aggregate reviews, identify buying signals, and generate personalized approach strategies - all while the rep is driving to their next appointment.\"\n\nKey features of the RepSpheres platform include:\n• Canvas Sales Intelligence: 95% confidence doctor research with NPI verification\n• Multi-LLM AI Support: Access to Claude, GPT-4, and Gemini for optimal results\n• Real-Time Competitive Analysis: Instant insights on local market dynamics\n• Automated Review Aggregation: Synthesis from multiple trusted sources\n• Batch Processing: Research hundreds of prospects simultaneously\n• Module-Based Architecture: Specialized tools for CRM, linguistics, market data, and more\n\nEarly adopters in the medical device industry have reported dramatic improvements in sales efficiency. Beta users experienced a 3x increase in qualified meetings and reduced research time by 85%. One dental implant sales team reported closing 40% more deals within their first month using Canvas.\n\nThe platform leverages cutting-edge technologies including OpenRouter for AI orchestration, Brave Search API for real-time web data, and Firecrawl for intelligent website analysis. With built-in transcription services, Twilio integration, and Stripe-powered subscription management, RepSpheres offers a complete sales enablement ecosystem.\n\nRepSpheres is available immediately with a free tier for individual sales reps and scalable enterprise plans. The company plans to expand beyond medical device sales to serve pharmaceutical, B2B software, and financial services sectors in Q2 2025.\n\nAbout RepSpheres: RepSpheres is a sales intelligence platform that empowers sales teams with AI-driven prospect research, competitive analysis, and personalized approach strategies. With modules spanning CRM, market insights, linguistics analysis, and more, RepSpheres serves as the complete operating system for modern sales organizations. The platform processes millions of data points daily to deliver actionable intelligence that drives revenue growth.\n\nMedia Contact:\nRepSpheres Press Team\npress@repspheres.com\nhttps://repspheres.com\nhttps://canvas.repspheres.com\n\n###",
  "category": "Technology",
  "tags": ["RepSpheres", "AI", "sales intelligence", "medical device sales", "Canvas", "B2B software"],
  "companyName": "RepSpheres",
  "productName": "Canvas",
  "website": "https://repspheres.com",
  "demoUrl": "https://canvas.repspheres.com",
  "socialSnippet": "AI-powered sales intelligence platform achieves 95% confidence in prospect research",
  "leadParagraph": "RepSpheres launches comprehensive AI platform that transforms sales intelligence, reducing research time by 85% while increasing qualified meetings 3x."
}